README.rst
linecounter.py
setup.cfg
setup.py
linecounter.egg-info/PKG-INFO
linecounter.egg-info/SOURCES.txt
linecounter.egg-info/dependency_links.txt
linecounter.egg-info/entry_points.txt
linecounter.egg-info/top_level.txt