Metadata-Version: 1.0
Name: linecounter
Version: 1.2.0
Summary: linecounter for files
Home-page: https://github.com/halitkarakis/line-counter/
Author: M.Halit Karakis
Author-email: halit@halitkarakis.com.tr
License: Apache
Keywords: line counting tool
Platform: UNKNOWN
